qapp_qiskit/__init__.py
qapp_qiskit/async_tasks/__init__.py
qapp_qiskit/async_tasks/qiskit_circuit_export_task.py
qapp_qiskit/component/__init__.py
qapp_qiskit/component/backend/__init__.py
qapp_qiskit/component/backend/qiskit_invocation.py
qapp_qiskit/component/backend/qiskit_job_fetching.py
qapp_qiskit/factory/__init__.py
qapp_qiskit/factory/qiskit_device_factory.py
qapp_qiskit/factory/qiskit_handler_factory.py
qapp_qiskit/factory/qiskit_provider_factory.py
qapp_qiskit/handler/__init__.py
qapp_qiskit/handler/invocation_handler.py
qapp_qiskit/handler/job_fetching_handler.py
qapp_qiskit/model/__init__.py
qapp_qiskit/model/device/__init__.py
qapp_qiskit/model/device/ibm_cloud_device.py
qapp_qiskit/model/device/ibm_quantum_device.py
qapp_qiskit/model/device/oqc_cloud_device.py
qapp_qiskit/model/device/qapp_qiskit_device.py
qapp_qiskit/model/device/qiskit_device.py
qapp_qiskit/model/provider/__init__.py
qapp_qiskit/model/provider/ibm_cloud_provider.py
qapp_qiskit/model/provider/ibm_quantum_provider.py
qapp_qiskit/model/provider/oqc_cloud_provider.py
qapp_qiskit/model/provider/qapp_qiskit_provider.py
qapp_qiskit-0.0.12.dist-info/LICENSE
qapp_qiskit-0.0.12.dist-info/METADATA
qapp_qiskit-0.0.12.dist-info/WHEEL
qapp_qiskit-0.0.12.dist-info/top_level.txt
qapp_qiskit-0.0.12.dist-info/RECORD
