Metadata-Version: 2.2
Name: qapp-qiskit
Version: 0.0.12
Summary: QApp common library supporting QApp Platform for Quantum Computing
Author-email: "CITYNOW Co. Ltd. " <corp@citynow.vn>
License: The MIT License (MIT)
Project-URL: Homepage, https://citynow.asia/
Keywords: qapp,qapp-qiskit,quantum
Classifier: License :: OSI Approved :: MIT License
Classifier: Programming Language :: Python
Classifier: Programming Language :: Python :: 3
Requires-Python: <3.11,>=3.9
License-File: LICENSE
Requires-Dist: oqc-qcaas-client==3.12.0
Requires-Dist: qapp-common==0.0.10
Requires-Dist: qiskit-aer==0.16.1
Requires-Dist: qiskit-ibm-runtime==0.35.0
Requires-Dist: qiskit==1.3.2
Provides-Extra: dev
Requires-Dist: black; extra == "dev"
Requires-Dist: bumpver; extra == "dev"
Requires-Dist: isort; extra == "dev"
Requires-Dist: pip-tools; extra == "dev"
Requires-Dist: pytest; extra == "dev"
